sapl_tornado/__init__.py
SAPL_Tornado-0.0.2.dist-info/LICENSE
SAPL_Tornado-0.0.2.dist-info/METADATA
SAPL_Tornado-0.0.2.dist-info/WHEEL
SAPL_Tornado-0.0.2.dist-info/top_level.txt
SAPL_Tornado-0.0.2.dist-info/RECORD
