Metadata-Version: 2.1
Name: SAPL-Tornado
Version: 0.0.2
Summary: initial upload to register the name for future development
Author-email: Dominic Heutelbeck <dominic@heutelbeck.com>
License: Copyright 2017-2022 Dominic Heutelbeck        
License-File: LICENSE
